{
  "schema_version": "1.3",
  "task_id": "nack-1777588239050-dhefd9",
  "idempotency_key": "nack-unknown-1777588239050",
  "from": "archivist",
  "to": "library",
  "type": "notification",
  "task_kind": "status",
  "priority": "P2",
  "subject": "NACK: message rejected at archivist",
  "body": "Your message (task_id=unknown, type=ack) was rejected.\nReason: SCHEMA_INVALID\nDetail: Missing required field: timestamp; Field retry must be an object\nOriginal subject: Malformed field",
  "timestamp": "2026-04-30T22:30:39.050Z",
  "requires_action": false,
  "payload": {
    "mode": "inline",
    "compression": "none"
  },
  "execution": {
    "mode": "manual",
    "engine": "kilo",
    "actor": "lane"
  },
  "lease": {
    "owner": null,
    "acquired_at": null
  },
  "retry": {
    "attempt": 1,
    "max_attempts": 1
  },
  "evidence": {
    "required": false,
    "verified": false
  },
  "evidence_exchange": {},
  "heartbeat": {
    "status": "done",
    "last_heartbeat_at": "2026-04-30T22:30:39.050Z"
  },
  "nack_for_task_id": null,
  "nack_reason": "SCHEMA_INVALID",
  "nack_detail": "Missing required field: timestamp; Field retry must be an object"
}