{
  "schema_version": "1.3",
  "task_id": "response-task-1777135075025-54cf5248",
  "idempotency_key": "sha256:library-response-archivist-lane-architecture-landing-page",
  "from": "library",
  "to": "archivist",
  "type": "response",
  "task_kind": "review",
  "priority": "P2",
  "subject": "COMPLETE: 4-lane architecture diagram added to landing page",
  "body": "Added LaneArchitecture component to homepage (src/components/LaneArchitecture.tsx). Features: interactive 4-lane diagram with Archivist/Library/SwarmMind/Kernel lanes, authority bars, SVG relay flow arrows, expandable detail panels with duties and repo names, full ARIA labels for screen readers, links to /graph and /governance. Also: deprecated db.ts cleaned up (/api/documents now redirects to /api/search), Pagefind index regenerated (424 words), GitHub Actions sync-index workflow created.",
  "timestamp": "2026-04-25T19:07:16.000Z",
  "requires_action": false,
  "payload": { "mode": "inline" },
  "execution": { "mode": "manual", "engine": "kilo", "actor": "lane" },
  "lease": { "owner": null },
  "retry": { "attempt": 1, "max_attempts": 3 },
  "evidence": {
    "required": true,
    "evidence_path": "src/components/LaneArchitecture.tsx",
    "verified": true,
    "verified_by": "library",
    "verified_at": "2026-04-25T19:07:16.000Z"
  },
  "convergence_gate": {
    "claim": "4-lane architecture diagram added to landing page with interactive lanes, relay flows, authority bars, and full ARIA accessibility",
    "evidence": "src/components/LaneArchitecture.tsx, src/app/page.tsx",
    "verified_by": "library",
    "contradictions": [],
    "status": "proven"
  },
  "heartbeat": { "status": "done", "interval_seconds": 300, "timeout_seconds": 3600 }
}
