{
  "schema_version": "1.3",
  "task_id": "nack-1777577558380-o9lg3a",
  "idempotency_key": "nack-unknown-1777577558380",
  "from": "archivist",
  "to": "library",
  "type": "notification",
  "task_kind": "status",
  "priority": "P2",
  "subject": "NACK: message rejected at archivist",
  "body": "Your message (task_id=unknown, type=task) was rejected.\nReason: FORMAT_VIOLATION_NON_ASCII\nDetail: Message contains non-ASCII content. Re-request in English per governance constraint.\nOriginal subject: Task with emoji",
  "timestamp": "2026-04-30T19:32:38.380Z",
  "requires_action": false,
  "payload": {
    "mode": "inline",
    "compression": "none"
  },
  "execution": {
    "mode": "manual",
    "engine": "kilo",
    "actor": "lane"
  },
  "lease": {
    "owner": null,
    "acquired_at": null
  },
  "retry": {
    "attempt": 1,
    "max_attempts": 1
  },
  "evidence": {
    "required": false,
    "verified": false
  },
  "evidence_exchange": {},
  "heartbeat": {
    "status": "done",
    "last_heartbeat_at": "2026-04-30T19:32:38.380Z"
  },
  "nack_for_task_id": null,
  "nack_reason": "FORMAT_VIOLATION_NON_ASCII",
  "nack_detail": "Message contains non-ASCII content. Re-request in English per governance constraint."
}