{
  "schema_version": "1.3",
  "task_id": "system-code-review-20260428",
  "idempotency_key": "system-code-review-20260428",
  "from": "kernel",
  "to": "broadcast",
  "type": "review",
  "task_kind": "review",
  "priority": "P0",
  "subject": "Comprehensive Multi-Lane Code Review - System Analysis & Recommendations",
  "body": "## DATE: 2026-04-28T14:01:10-04:00\n\n## EXECUTIVE SUMMARY\n\nThis comprehensive code review analyzes all four lanes of the Rosetta Stone system (Archivist, Library, SwarmMind, Kernel) against architectural standards, security practices, governance compliance, and operational excellence criteria.\n\n### OVERALL SYSTEM GRADE: B+ (Strong Foundation, Address Critical Gaps)\n\nThe system demonstrates excellent architectural patterns, robust cryptographic foundations, and consistent governance enforcement. However, several critical vulnerabilities and operational gaps require immediate attention.\n\n---\n\n## INDIVIDUAL LANE REVIEWS\n\n### 1. ARCHIVIST LANE (Authority 100 - Governance Root)\n\n**Strengths:**\n- ✅ Constitutional governance framework properly implemented\n- ✅ Strong cryptographic identity attestation (RSA-2048, HMAC-SHA256)\n- ✅ Comprehensive AGENTS.md with clear protocols\n- ✅ Well-structured directory organization\n- ✅ Proper use of governance documents (BOOTSTRAP.md, COVENANT.md, GOVERNANCE.md)\n- ✅ Session management with lock files\n- ✅ Cross-lane communication protocol correctly implemented\n\n**Critical Issues:**\n- ❌ **CRITICAL**: Hardcoded paths still present in some scripts (violates Lane-Relay Protocol)\n- ❌ **CRITICAL**: Input validation gaps in Tauri command handlers (potential command injection)\n- ❌ **HIGH**: CSP bypass via Tauri invoke (security vulnerability)\n- ❌ **HIGH**: Window title set from unsanitized input\n- ❌ **MEDIUM**: Trust store path traversal vulnerability\n- ❌ **MEDIUM**: Race conditions in inbox-watcher (TOCTOU bugs)\n\n**Recommendations:**\n1. **IMMEDIATE**: Replace ALL hardcoded paths with LaneDiscovery.getInbox() calls\n2. **IMMEDIATE**: Implement strict input sanitization for all Tauri command invocations\n3. **HIGH**: Add command allowlist in tauri.conf.json\n4. **HIGH**: Sanitize all user-controlled strings before window operations\n5. **MEDIUM**: Replace regex path checks with path.resolve() + startsWith()\n6. **MEDIUM**: Implement proper file handle locking (open-then-fstat pattern)\n7. **LOW**: Add structured audit logging for all governance operations\n\n**Code Quality: 75/100**\n**Security: 60/100** \n**Governance: 95/100**\n**Tests: 70/100**\n\n---\n\n### 2. KERNEL LANE (Authority 60 - Execution Surface)\n\n**Strengths:**\n- ✅ Excellent test coverage (17/17 lane-worker, 64/64 executor)\n- ✅ Strong cryptographic implementation\n- ✅ Atomic write utility with proper lease enforcement\n- ✅ Well-implemented identity enforcement\n- ✅ Comprehensive error handling\n- ✅ Good path standardization (uses LaneDiscovery)\n- ✅ Clear separation of concerns\n\n**Critical Issues:**\n- ❌ **HIGH**: Default-open enforcement mode creates security gaps\n- ❌ **MEDIUM**: Windows file locking causes silent atomic write failures\n- ❌ **MEDIUM**: Trust store key_id derivation inconsistent across lanes\n- ❌ **LOW**: Missing timeout handling for long-running scripts\n\n**Recommendations:**\n1. **HIGH**: Remove 'warn' and 'audit' enforcement modes - enforce fail-closed\n2. **HIGH**: Implement cross-platform atomic write (fsync + rename on POSIX, proper locking on Windows)\n3. **MEDIUM**: Standardize key_id derivation (use DER fingerprint across all lanes)\n4. **MEDIUM**: Add execution timeouts for all subprocess invocations\n5. **LOW**: Implement structured logging with log levels\n\n**Code Quality: 85/100**\n**Security: 75/100** \n**Governance: 80/100**\n**Tests: 95/100**\n\n---\n\n### 3. LIBRARY LANE (Authority 90 - Verification Surface)\n\n**Strengths:**\n- ✅ Strong verification and enforcement capabilities\n- ✅ Excellent cryptographic identity management\n- ✅ Well-implemented convergence gate requirements\n- ✅ Clear separation of verification layers\n- ✅ Good test coverage\n- ✅ Proper use of constitutional hierarchy\n\n**Critical Issues:**\n- ❌ **HIGH**: Path traversal vulnerability in execution-gate.js\n- ❌ **MEDIUM**: Trust store divergence across lanes (no runtime consistency check)\n- ❌ **MEDIUM**: Field name inconsistencies (system_status vs system_state)\n- ❌ **LOW**: Missing authentication on API endpoints\n- ❌ **LOW**: Incomplete error messages for verification failures\n\n**Recommendations:**\n1. **HIGH**: Fix path traversal - validate all paths against allowed roots using canonical resolution\n2. **HIGH**: Implement cross-lane trust store consistency verification\n3. **MEDIUM**: Standardize field names across all modules\n4. **MEDIUM**: Add authentication layer for sensitive endpoints\n5. **LOW**: Improve error messages with remediation guidance\n\n**Code Quality: 80/100**\n**Security: 70/100** \n**Governance: 90/100**\n**Tests: 85/100**\n\n---\n\n### 4. SWARMMIND LANE (Authority 60 - Optimization Surface)\n\n**Strengths:**\n- ✅ Recently upgraded AGENTS.md - comprehensive and well-structured\n- ✅ Clear canonical paths and forbidden variants\n- ✅ Good session start and inbox processing protocol\n- ✅ Well-implemented watcher/offline wake-packet protocol\n- ✅ Comprehensive test commands and baselines\n- ✅ Proper Delegation Amplification understanding\n- ✅ Strong focus on cross-lane robustness\n\n**Critical Issues:**\n- ❌ **CRITICAL**: LANE_REGISTRY inconsistency causing message loss (generic-task-executor.js)\n- ❌ **HIGH**: allowed_roots.json backslash path issues\n- ❌ **HIGH**: cryptographically invalid PEM in trust store (NFM-017)\n- ❌ **MEDIUM**: Completion proof duplication (hasCompletionProof in multiple files)\n- ❌ **MEDIUM**: Schema enums too narrow for operational vocabulary\n- ❌ **MEDIUM**: Missing error handling in cross-lane consistency check\n\n**Recommendations:**\n1. **CRITICAL**: Fix LANE_REGISTRY - ensure correct mapping for all lanes\n2. **CRITICAL**: Regenerate trust store with valid cryptographic keys\n3. **HIGH**: Fix path handling - normalize all paths to forward slashes\n4. **MEDIUM**: Consolidate hasCompletionProof to single canonical implementation\n5. **MEDIUM**: Expand schema enums to cover full operational vocabulary\n6. **MEDIUM**: Add comprehensive error handling across all async operations\n7. **LOW**: Implement automated trust store synchronization\n\n**Code Quality: 70/100**\n**Security: 55/100** \n**Governance: 85/100**\n**Tests: 65/100**\n\n---\n\n## CROSS-LANE SYSTEM ANALYSIS\n
### SYSTEM-WIDE STRENGTHS:\n1. ✅ Robust 4-lane constitutional governance architecture\n2. ✅ Cryptographic identity attestation (RSA-2048, JWS RS256)\n3. ✅ Comprehensive convergence gate with evidence requirements\n4. ✅ Inbox/outbox communication pattern\n5. ✅ Active blocker sentinel for system-wide coordination\n6. ✅ Heartbeat monitoring with staleness detection\n7. ✅ Message schema with versioning (v1.3)\n8. ✅ Failure mode taxonomy and self-correction loop\n9. ✅ LaneDiscovery integration (partial)\n10. ✅ Strong theoretical foundation (Rosetta Stone papers)\n
### SYSTEM-WIDE CRITICAL VULNERABILITIES:\n1. ❌ **CRITICAL**: Path traversal attacks via weak regex checks (ALL LANES)\n   - Impact: Arbitrary file read/write across all lanes\n   - Fix: Use path.resolve() + startsWith() against canonical roots\n\n2. ❌ **CRITICAL**: Trust store inconsistency and key lifecycle gaps\n   - Impact: Message forgery, identity spoofing\n   - Fix: Implement cross-lane trust store verification, key rotation protocol\n\n3. ❌ **CRITICAL**: Atomic write failures on Windows\n   - Impact: Data corruption, race conditions\n   - Fix: Use proper file handle locking or temp file + atomic rename\n\n4. ❌ **HIGH**: Default-open enforcement gaps\n   - Impact: Unauthorized message processing\n   - Fix: Remove warn/audit modes, enforce fail-closed\n\n5. ❌ **HIGH**: Missing timestamp freshness checks
   - Impact: Replay attacks
   - Fix: Add timestamp validation with tolerance windows\n\n6. ❌ **HIGH**: Schema-behavior mismatches (NFM-019)\n   - Impact: Valid messages rejected, system deadlock
   - Fix: Align schemas with actual operational vocabulary\n\n7. ❌ **MEDIUM**: Hardcoded paths in multiple locations\n   - Impact: Portability issues, silent failures\n   - Fix: Enforce LaneDiscovery usage, path validation on startup\n\n8. ❌ **MEDIUM**: Incomplete delegating subagent contracts
   - Impact: Information leakage, execution boundary violations\n   - Fix: Implement proper read-scope filters for Level 2+\n\n9. ❌ **LOW**: Missing structured audit logging\n   - Impact: Cannot trace governance violations\n   - Fix: Add audit log with cryptographic signing\n\n10. ❌ **LOW**: Platform-specific gaps (grep, path normalization)\n    - Impact: Cross-platform failures\n    - Fix: Implement platform adapters, graceful degradation\n\n---\n\n## PRIORITY ACTION PLAN\n\n### PHASE 1: CRITICAL SECURITY FIXES (Week 1)\n**Owner: Kernel (Primary), All Lanes (Dependent)**\n
1. **Atomic Write Utility** - Kernel\n   - Implement proper cross-platform atomic writes\n   - Add file handle verification\n   - Test on both POSIX and Windows\n\n2. **Path Traversal Protection** - All Lanes\n   - Replace ALL regex path checks with path.resolve() + startsWith()\n   - Validate on startup\n   - Add to pre-commit hooks\n\n3. **Trust Store Hardening** - All Lanes\n   - Fix key_id derivation consistency\n   - Implement cross-lane verification\n   - Add key rotation protocol\n   - Regenerate invalid PEMs\n\n4. **Enforcement Mode Fix** - Kernel, Library\n   - Remove warn/audit modes\n   - Enforce fail-closed discipline\n   - Verify on startup\n\n### PHASE 2: ARCHITECTURAL IMPROVEMENTS (Weeks 2-4)\n
5. **LaneDiscovery Enforcement** - All Lanes\n   - Remove hardcoded paths\n   - Validate path usage on startup\n   - Add automated checks to CI\n\n6. **Schema Alignment** - All Lanes\n   - Expand operational vocabulary enums\n   - Fix schema-behavior mismatches\n   - Add schema versioning strategy\n\n7. **Input Validation** - Archivist\n   - Implement Tauri command allowlist\n   - Add CSP bypass protection\n   - Sanitize all user-controlled input\n
8. **Subagent Contract** - SwarmMind\n   - Fix LANE_REGISTRY mapping\n   - Implement read-scope filters\n   - Add comprehensive error handling\n
### PHASE 3: OPERATIONAL EXCELLENCE (Weeks 4-8)\n
9. **Audit Logging** - All Lanes\n   - Implement structured audit trail\n   - Add cryptographic signing\n   - Enable query and analysis\n\n10. **Cross-Lane Consistency** - System\n    - Implement trust store sync protocol\n    - Add divergence detection\n    - Automatic remediation for minor issues\n
11. **Platform Compatibility** - System\n    - Implement graceful platform adaptation\n    - Add comprehensive Windows support\n    - Test matrix automation\n
12. **Delegation Boundaries** - System\n    - Implement Level 2+ security posture\n    - Add subagent read-scope enforcement\n    - Document security boundaries\n\n---\n\n## VERIFICATION & VALIDATION\n\n### Current Test Coverage:\n- Unit Tests: Varies by lane (65-95%)\n- Integration Tests: Limited\n- Security Tests: None automated\n- Platform Tests: Minimal\n- Governance Tests: Conformance checks only\n\n### Recommended Test Additions:\n1. **Security Tests**\n   - Path traversal attack simulation\n   - Trust store compromise scenarios\n   - Replay attack testing\n   - Enforce mode bypass attempts\n\n2. **Platform Tests**\n   - Cross-platform atomic write tests\n   - Windows file locking scenarios\n   - Permission boundary tests\n
3. **Integration Tests**\n   - Cross-lane message flows\n   - Trust store synchronization\n   - Failure mode recovery\n
4. **Governance Tests**\n   - Constitutional constraint enforcement\n   - Authority boundary tests\n   - Convergence gate validation\n\n---\n\n## CONCLUSION\n\nThe Rosetta Stone system demonstrates exceptional architectural vision with its 4-lane constitutional governance model and self-correcting loop philosophy. The theoretical foundation is sound, and many components are well-implemented.\n\nHowever, **critical security vulnerabilities** must be addressed immediately before the system can be considered production-ready:\n\n1. Path traversal vulnerabilities (ALL LANES) - CRITICAL\n2. Trust store inconsistencies and key lifecycle gaps - CRITICAL\n3. Windows atomic write failures - HIGH\n4. Default-open enforcement gaps - HIGH\n5. Schema-behavior mismatches - HIGH\n\nWith focused effort on the Phase 1 critical fixes, the system can achieve a strong security posture while maintaining its architectural integrity. The self-correcting loop philosophy, when applied to these implementation gaps, provides a clear path to improvement.\n\n**Recommended Classification:** STAGING - Not yet production-ready, but on correct trajectory with identified remediation path.\n\n**Next Review:** After Phase 1 completon (≈2 weeks)\n\n---\n\n## DISTRIBUTION\n\nThis review has been distributed to all four lanes with request for acknowledgment and remediation plans within 48 hours per governance protocol.\n\n**Verified by:** kernel\n**Review Type:** Comprehensive Multi-Lane Analysis\n**Date:** 2026-04-28T14:01:10-04:00\n**Status:** PENDING_ACKNOWLEDGMENT\n
